{
  "DEV": {
    "HEADER": "Kehitys ja suunnittelu",
    "NAMES": [
      "Anthony Giovannetti",
      "Casey Yano"
    ]
  },
  "OPS": {
    "HEADER": "Toiminnot ja metriikat",
    "NAMES": [
      "Danielle Jenkins",
      "Jake Rabinowitz"
    ]
  },
  "SOUND": {
    "HEADER": "Musiikki ja äänet",
    "NAMES": [
      "Clark Aboud"
    ]
  },
  "VOICE": {
    "HEADER": "Ääninäyttelijät",
    "NAMES": [
      "Tamara Ryan",
      "Michael Schwalbe"
    ]
  },
  "PORTRAITS": {
    "HEADER": "Korttien piirrokset ja tapahtumien taide",
    "NAMES": [
      "Anailis Dorta"
    ]
  },
  "ANIMATION": {
    "HEADER": "Hahmoanimaatiot",
    "NAMES": [
      "Julio Duque Montero",
      "Jon Sandler"
    ]
  },
  "ILLUSTRATION": {
    "HEADER": "Promo- ja taustakuvitukset",
    "NAMES": [
      "Bruce Brenneise"
    ]
  },
  "LOC_ZHS": {
    "HEADER": "Kiinan (yksinkertaistettu) lokalisaatio",
    "NAMES": [
      "Sound of Mystery"
    ]
  },
  "LOC_ZHT": {
    "HEADER": "Kiinan (perinteinen) lokalisaatio",
    "NAMES": []
  },
  "LOC_FRA": {
    "HEADER": "Ranskan lokalisaatio",
    "NAMES": [
      "Xavier \"Blagatt\" Dupont",
      "Malik \"Devexia\" Leonarski",
      "Thomas \"Elgerine\" Ferry",
      "Vincent \"Henip\" Bartoux",
      "Alexandre \"Judgy\" Gaubert",
      "Vincent \"MissingNoShiny\" Larcin",
      "Nicky \"Qazahar\" Dehout",
      "Julien \"RoPeTTe\" Ropero",
      "Hugo \"Tagadda\" Vurpillot",
      "Corentin \"Tchus\" Monfort",
      "Zachary \"WyvernZed\" Janisse"
    ]
  },
  "LOC_DEU": {
    "HEADER": "Saksan lokalisaatio",
    "NAMES": [
      "Joshua \"Joshipon\" Wiegand "
    ]
  },
  "LOC_ITA": {
    "HEADER": "Italian lokalisaatio",
    "NAMES": [
      "Hob",
      "Mero Marco",
      "Luigi Squarzina"
    ]
  },
  "LOC_JPN": {
    "HEADER": "Japanin lokalisaatio",
    "NAMES": [
      "Grezzz"
    ]
  },
  "LOC_KOR": {
    "HEADER": "Korean lokalisaatio",
    "NAMES": [
      "Käännöspäällikkö:",
      "Eteriny",
      "Käännös:",
      "Simcoding",
      "DesFrog",
      "insight",
      "K4lium",
      "hina",
      "Steam-sivun käännös:",
      "GyeRyak"
    ]
  },
  "LOC_NOR": {
    "HEADER": "Norjan lokalisaatio",
    "NAMES": [
      "Eystein Jarp"
    ]
  },
  "LOC_POL": {
    "HEADER": "Puolan lokalisaatio",
    "NAMES": [
      "Käännökset ja koordinointi:",
      "Stanis³aw \"ST4H\" Borkowski",
      "Oskar \"volf3n\" Nowak",
      "Lisäkäännökset:",
      "Adrian \"xeros\" Rolka",
      "Oikoluku:",
      "Oskar \"volf3n\" Nowak",
      "Ehdotukset ja palaute:",
      "Kasper \"Awokado\" Beræ",
      "Pawe³ \"BASTIL\" Kaleta",
      "Grzegorz \"GregPL\" Bogus³awski",
      "Erwin \"mateusz3010\" Matys",
      "Mettie",
      "Rafa³ \"SponTon83\" Szyszko"
    ]
  },
  "LOC_PTB": {
    "HEADER": "Brasilianportugalin lokalisaatio",
    "NAMES": [
      "Guilherme \"GPerego\" Perego",
      "Gustavo \"KomKlave\" Duarte",
      "José \"Maneimax\" Vasconcelos",
      "Leonardo \"Iikat\" Takii",
      "Nathan \"NoxShadow\" Cervieri",
      "Paulo \"SilverTape\" Hauck"
    ]
  },
  "LOC_RUS": {
    "HEADER": "Venäjän lokalisaatio",
    "NAMES": [
      "Käännökset ja koordinointi:",
      "Ivan \"Ingrett\" Khoroshunenko",
      "Käännökset ja repo:",
      "Vladislav \"Vlad-00003\" Bolshakov",
      "Ehdotukset ja palaute:",
      "Mikhail \"Outmind\" Dyuzhev",
      "Bohdan \"DarkRosse\" Kalytiuk",
      "Sergey \"lol10801lol\" K.",
      "Ascimator",
      "Kateryna \"Meds\" Belimenko-Bolger",
      "Alexey \"Surrealistic Ganerson\" Popov",
      "Alexandr \"LiaNdrY\" Mazistov"
    ]
  },
  "LOC_TUR": {
    "HEADER": "Turkin lokalisaatio",
    "NAMES": [
      "Erdem Gürbüz"
    ]
  },
  "LOC_ADDITIONAL": {
    "HEADER": "Lisäkäännökset",
    "NAMES": [
      "MoGi Group"
    ]
  },
  "TEST": {
    "HEADER": "Pelitestaajat",
    "NAMES": [
      "Agari",
      "Daria Anderson",
      "Zac Bauermeister",
      "Nick Becker",
      "Esther Beckman",
      "Leo Chen",
      "Brian Chau",
      "Dan D'Argenio",
      "David Delorenzo",
      "Tim Erskine",
      "Benjamin Finkel",
      "Rajiv Giridharagopal",
      "Wyatt Grodzins",
      "Ren Howell",
      "Kyle James",
      "Ryan Mathisen",
      "Anthony McMillian",
      "Brad Meine",
      "Jacob Morris",
      "Alex Rockwell",
      "Greg Scheopner",
      "John \"Slide20xl\" Smith",
      "Aaron Taggart",
      "Alexander Toy",
      "Merijn van der Vliet",
      "David Von Derau",
      "Conor Watson"
    ]
  },
  "SPECIAL": {
    "HEADER": "Erityiskiitokset",
    "NAMES": [
      "Harry Rabinowitz",
      "Kevin \"Billy\" Matheson",
      "Anthony Roybal",
      "Lee Beckman",
      "Sam Welch",
      "feedbackbot",
      "Evan Howell",
      "Justin Myhres",
      "robojumper"
    ]
  },
  "THANKS_MSG": {
    "HEADER": "...ja kiitos SINULLE kun pelasit!",
    "NAMES": []
  }
}